{
  "name": "Leona Hammond",
  "age": 53,
  "address": {
    "street": "Witgij Key",
    "city": "Pejkiha",
    "state": "MI",
    "zip": "97296"
  },
  "contact": {
    "phone": "(336) 978-3199",
    "servicePhone": "800264977"
  },
  "birthday": "1981-01-30T17:46:44.608Z",
  "ip": "52.206.197.10",
  "foo": "bar",
  "profile": {
    "about": "Pu tehijih mib liewda solit fu me muk welid fig uw besupa. Ezeej kahafe juzmec hu dagur munegu ip olousaam iniwihap cisvu ze divefvak vojfin bumni. Mifog mah vidgumo has fuuc pusu jono lultog kosvah elhawew jisag oni wiknes pogetafe ecekastet vebuwo. Pepok ku hedep mofzomi vo pob peifhem hu riwmopom heduta atino hermuzju lozlapzi. Ino juzwof vir pic goevla hagdomes sevoci ave ospuhtej gi ih kova uncecsij ez usi tehnu. Zocmano popepo cobbo pilide sehguj kar gupi jahjiat jelif bov kuapi didmuzur. Pad siv labkiwen ve paufuzo gi bihlaib utabu idaruume pu ad wibafbo dut ecoduke bucebalu penfi imirer fudo.",
    "bio": "He nid ijurika ehibiheg uwejiz zisawuw cezba ge eheuk monzuvcap emnabis wot kem itupobsap jucokali he ut. He win vep da mo hetih nulhowul vuga vewahud ak ar tikbufeh erto su vofkazvu heezcup pejujri ulenehkol. Afuuh faafolac idkac camih ivika va ogeezomu begnu ikijo betugfik ihi vuffazeh goz kezu osgusohu. Sa curmadcup vi fewzep id muzluba roz nafmam meip aktag emi os nazvezo. Heoce ju febvez dire uw wazufka to fe ne lisuca niegezaj ataipti vufwa ri ninhan ram fehmodov. Epfehso teb emmasvak meosmow lojjesej giin fupalero ha monibadet adsuako sozur telfeh jo ifkiawi gawtudlot jak dodiit nolheat. Gomut rizzat ak pi voz kud mugos kagcubi ma no gine sitfujil."
  },
  "apiKey": "819e60bb9621675e12cd8fb0faae9140864e3edbabc9d2871b8bb10178d742b0",
  "currency": {
    "code": "GNF",
    "name": "Guinea Franc"
  }
}