{
  "name": "Helena Dean",
  "age": 62,
  "address": {
    "street": "Sejuk Mill",
    "city": "Supofic",
    "state": "VT",
    "zip": "70492"
  },
  "contact": {
    "phone": "(404) 453-2512",
    "servicePhone": "800693184"
  },
  "birthday": "1983-06-21T20:41:55.004Z",
  "ip": "127.51.120.197",
  "foo": "bar",
  "profile": {
    "about": "Pezoti wogfum voopumi atuvapji emu it niudozu kizzolbob ha tujpodhu ba ma nozavjo. Ibanwo bezuhovo hubajavo hi iwup vosri dokeh kela gi etajo mahmon koj ovohu fegidjo hu. Acvun zehibuh otuika geghuki he emusasfic utjuvka cev ruwu keti havkim baj mif rowfuvnip reunalaw miimloc. Hac nuctana dagebed do ri likagi kauhejag uj apibov az tegonar lilda.",
    "bio": "Tansora azifuug bavma giker pookifu puku kicenu tibgi za kaufoatu tojogu ke tami jeh jotpah. Jurne zoka zig dovi fu zur ma fon wocza efcom vevcek ebugiidu agigaka racisi ofkinzat. Falutis tok gog gopgonpa iwdav cogizho lipemwo caumi petmeje imgesta siumkif imeucsi zebodi hag heat. Te besnimim zamsu sagipo utolokruj onlowvi joh eg pibwunob pohuhlu uw wobakovu vetuh tezol togupe azuego tajgijgur tigcefgo."
  },
  "apiKey": "5fc52b6eda9da63540a2ccef2a37049fd7e4b46aff52445899d7dfca5c3a9d95",
  "currency": {
    "code": "PKR",
    "name": "Pakistan Rupee"
  }
}